[{"item":"fairly popular (70 - 80)","support":191},{"item":"somewhat popular (60 - 70)","support":130},{"item":"popular (50 - 60)","support":121},{"item":"very popular (80 - 90)","support":88},{"item":"in","support":77},{"item":"the","support":66},{"item":"no","support":54},{"item":"genre: rock","support":50},{"item":"genre: pop","support":50},{"item":"genre: classical","support":50},{"item":"genre: r&b","support":50},{"item":"genre: jazz","support":50},{"item":"genre: country","support":50},{"item":"genre: Metal","support":50},{"item":"genre: folk","support":49},{"item":"genre: rap","support":49},{"item":"not very popular (0 - 50)","support":48},{"item":"genre: edm","support":48},{"item":"genre: blues","support":48},{"item":"genre: reggae","support":47},{"item":"i","support":41},{"item":"you","support":39},{"item":"a","support":35},{"item":"piano","support":34},{"item":"op","support":34},{"item":"sonata","support":33},{"item":"remastered","support":32},{"item":"me","support":31},{"item":"major","support":30},{"item":"love","support":30},{"item":"feat","support":29},{"item":"version","support":24},{"item":"of","support":24},{"item":"to","support":22},{"item":"it","support":19},{"item":"with","support":17},{"item":"on","support":17},{"item":"my","support":16},{"item":"for","support":16},{"item":"most popular (90 - 100)","support":13},{"item":"and","support":13},{"item":"ii","support":13},{"item":"like","support":11},{"item":"blue","support":10},{"item":"up","support":10},{"item":"minor","support":10},{"item":"allegro","support":10},{"item":"dont","support":9},{"item":"your","support":9},{"item":"iii","support":9},{"item":"girls","support":8},{"item":"from","support":8},{"item":"remaster","support":8},{"item":"one","support":8},{"item":"girl","support":7},{"item":"be","support":7},{"item":"im","support":7},{"item":"all","support":7},{"item":"g","support":7},{"item":"adagio","support":7},{"item":"what","support":7},{"item":"time","support":7},{"item":"way","support":7},{"item":"aint","support":7},{"item":"is","support":7},{"item":"cant","support":7},{"item":"suite","support":7},{"item":"black","support":6},{"item":"e","support":6},{"item":"andante","support":6},{"item":"man","support":6},{"item":"digital","support":6},{"item":"take","support":6},{"item":"back","support":6},{"item":"go","support":6},{"item":"got","support":6},{"item":"this","support":6},{"item":"und","support":6},{"item":"sweet","support":5},{"item":"its","support":5},{"item":"little","support":5},{"item":"let","support":5},{"item":"1998","support":5},{"item":"2015","support":5},{"item":"name","support":5},{"item":"home","support":5},{"item":"again","support":5},{"item":"bad","support":5},{"item":"f","support":5},{"item":"la","support":5},{"item":"eyes","support":5},{"item":"at","support":5},{"item":"song","support":5},{"item":"cantabile","support":5},{"item":"remix","support":5},{"item":"mit","support":5},{"item":"when","support":5},{"item":"world","support":4},{"item":"so","support":4},{"item":"1","support":4},{"item":"more","support":4},{"item":"hey","support":4},{"item":"bwv","support":4},{"item":"1007","support":4},{"item":"live","support":4},{"item":"down","support":4},{"item":"are","support":4},{"item":"get","support":4},{"item":"27","support":4},{"item":"heart","support":4},{"item":"a-flat","support":4},{"item":"do","support":4},{"item":"green","support":4},{"item":"new","support":4},{"item":"long","support":4},{"item":"stop","support":4},{"item":"ma","support":4},{"item":"non","support":4},{"item":"troppo","support":4},{"item":"e-flat","support":4},{"item":"original","support":4},{"item":"vivace","support":4},{"item":"dream","support":4},{"item":"good","support":4},{"item":"that","support":4},{"item":"28","support":4},{"item":"101","support":4},{"item":"29","support":4},{"item":"b-flat","support":4},{"item":"106","support":4},{"item":"hammerklavier","support":4},{"item":"molto","support":4},{"item":"change","support":3},{"item":"slide","support":3},{"item":"stay","support":3},{"item":"pie","support":3},{"item":"mr","support":3},{"item":"loved","support":3},{"item":"son","support":3},{"item":"rain","support":3},{"item":"album","support":3},{"item":"soul","support":3},{"item":"gonna","support":3},{"item":"feel","support":3},{"item":"solo","support":3},{"item":"moonlight","support":3},{"item":"à","support":3},{"item":"mama","support":3},{"item":"oh","support":3},{"item":"rock","support":3},{"item":"dance","support":3},{"item":"boy","support":3},{"item":"know","support":3},{"item":"ill","support":3},{"item":"c-sharp","support":3},{"item":"say","support":3},{"item":"hurricane","support":3},{"item":"better","support":3},{"item":"could","support":3},{"item":"sostenuto","support":3},{"item":"id","support":3},{"item":"too","support":3},{"item":"wanna","support":3},{"item":"2002","support":3},{"item":"23","support":3},{"item":"57","support":3},{"item":"appassionata","support":3},{"item":"life","support":3},{"item":"not","support":3},{"item":"fall","support":3},{"item":"gucci","support":3},{"item":"right","support":3},{"item":"26","support":3},{"item":"low","support":3},{"item":"81a","support":3},{"item":"les","support":3},{"item":"adieux","support":3},{"item":"wild","support":3},{"item":"25","support":3},{"item":"79","support":3},{"item":"different","support":3},{"item":"here","support":3},{"item":"fear","support":3},{"item":"nothing","support":3},{"item":"empfindung","support":3},{"item":"now","support":3},{"item":"cry","support":3},{"item":"espressivo","support":3},{"item":"angel","support":3},{"item":"fire","support":3},{"item":"over","support":3},{"item":"georgia","support":3},{"item":"30","support":3},{"item":"109","support":3},{"item":"lonely","support":3},{"item":"31","support":3},{"item":"together","support":3},{"item":"110","support":3},{"item":"no1","support":3},{"item":"nocturne","support":3},{"item":"middle","support":2},{"item":"wagon","support":2},{"item":"put","support":2},{"item":"spell","support":2},{"item":"wheel","support":2},{"item":"case","support":2},{"item":"pride","support":2},{"item":"joy","support":2},{"item":"fooled","support":2},{"item":"around","support":2},{"item":"fell","support":2},{"item":"yeah","support":2},{"item":"onions","support":2},{"item":"country","support":2},{"item":"by","support":2},{"item":"2004","support":2},{"item":"boom","support":2},{"item":"welcome","support":2},{"item":"sally","support":2},{"item":"city","support":2},{"item":"single","support":2},{"item":"enter","support":2},{"item":"hill","support":2},{"item":"midnight","support":2},{"item":"after","support":2},{"item":"sandman","support":2},{"item":"sorry","support":2},{"item":"florida","support":2},{"item":"woman","support":2},{"item":"line","support":2},{"item":"made","support":2},{"item":"shape","support":2},{"item":"stargazing","support":2},{"item":"rules","support":2},{"item":"friends","support":2},{"item":"stir","support":2},{"item":"reaper","support":2},{"item":"rita","support":2},{"item":"ora","support":2},{"item":"out","support":2},{"item":"closer","support":2},{"item":"years","support":2},{"item":"lauv","support":2},{"item":"some","support":2},{"item":"make","support":2},{"item":"alessia","support":2},{"item":"cara","support":2},{"item":"selena","support":2},{"item":"gomez","support":2},{"item":"else","support":2},{"item":"crazy","support":2},{"item":"rhapsody","support":2},{"item":"highway","support":2},{"item":"three","support":2},{"item":"child","support":2},{"item":"bridge","support":2},{"item":"california","support":2},{"item":"birds","support":2},{"item":"ever","support":2},{"item":"buffalo","support":2},{"item":"youre","support":2},{"item":"give","support":2},{"item":"light","support":2},{"item":"than","support":2},{"item":"summer","support":2},{"item":"murder","support":2},{"item":"walking","support":2},{"item":"youve","support":2},{"item":"friend","support":2},{"item":"mind","support":2},{"item":"they","support":2},{"item":"1999","support":2},{"item":"silence","support":2},{"item":"she","support":2},{"item":"water","support":2},{"item":"we","support":2},{"item":"wrote","support":2},{"item":"just","support":2},{"item":"boys","support":2},{"item":"sia","support":2},{"item":"where","support":2},{"item":"head","support":2},{"item":"digitally","support":2},{"item":"3","support":2},{"item":"vocal","support":2},{"item":"cheek","support":2},{"item":"ballad","support":2},{"item":"into","support":2},{"item":"mood","support":2},{"item":"romance","support":2},{"item":"square","support":2},{"item":"cello","support":2},{"item":"were","support":2},{"item":"forever","support":2},{"item":"but","support":2},{"item":"run","support":2},{"item":"boots","support":2},{"item":"prélude","support":2},{"item":"hell","support":2},{"item":"moon","support":2},{"item":"14","support":2},{"item":"soldier","support":2},{"item":"thing","support":2},{"item":"broken","support":2},{"item":"tears","support":2},{"item":"2","support":2},{"item":"questions","support":2},{"item":"can","support":2},{"item":"whiskey","support":2},{"item":"22","support":2},{"item":"praying","support":2},{"item":"54","support":2},{"item":"sky","support":2},{"item":"più","support":2},{"item":"drake","support":2},{"item":"come","support":2},{"item":"see","support":2},{"item":"vain","support":2},{"item":"assai","support":2},{"item":"feeling","support":2},{"item":"con","support":2},{"item":"work","support":2},{"item":"want","support":2},{"item":"if","support":2},{"item":"comes","support":2},{"item":"presto","support":2},{"item":"slow","support":2},{"item":"coming","support":2},{"item":"mix","support":2},{"item":"cold","support":2},{"item":"have","support":2},{"item":"das","support":2},{"item":"24","support":2},{"item":"f-sharp","support":2},{"item":"78","support":2},{"item":"thérèse","support":2},{"item":"money","support":2},{"item":"night","support":2},{"item":"dirty","support":2},{"item":"used","support":2},{"item":"africa","support":2},{"item":"90","support":2},{"item":"radio","support":2},{"item":"edit","support":2},{"item":"road","support":2},{"item":"dawn","support":2},{"item":"ready","support":2},{"item":"lebhaft","support":2},{"item":"drop","support":2},{"item":"nicht","support":2},{"item":"zu","support":2},{"item":"geschwind","support":2},{"item":"sehr","support":2},{"item":"iv","support":2},{"item":"32","support":2},{"item":"c","support":2},{"item":"111","support":2},{"item":"ed","support":2},{"item":"bam","support":2},{"item":"pretty","support":2},{"item":"peace","support":2},{"item":"mane","support":2},{"item":"was","support":2},{"item":"chicken","support":2},{"item":"queen","support":2},{"item":"town","support":2},{"item":"lil","support":2},{"item":"without","support":2},{"item":"bergamasque","support":2},{"item":"de","support":2},{"item":"lune","support":2},{"item":"thoughts","support":2},{"item":"true","support":2},{"item":"en","support":2},{"item":"violoncello","support":2}]